airscript/__init__.py
airscript/data.py
airscript/action/__init__.py
airscript/action/gesture.py
airscript/action/key.py
airscript/action/path.py
airscript/action/touch.py
airscript/graphics/__init__.py
airscript/intent/__init__.py
airscript/node/__init__.py
airscript/screen/__init__.py
airscript/system/Prgogress.py
airscript/system/__init__.py
airscript/ui/__init__.py
airscript/ui/dialog.py
airscript-0.0.8.dist-info/METADATA
airscript-0.0.8.dist-info/WHEEL
airscript-0.0.8.dist-info/top_level.txt
airscript-0.0.8.dist-info/RECORD
