Metadata-Version: 2.1
Name: airscript
Version: 0.0.8
Summary: airscript 类型提示语言包
Home-page: https://github.com/itisl2220/airscript
Author: ITisl
Author-email: aojoy@163.com
License: MIT
Keywords: python,airscript
Classifier: Programming Language :: Python :: 3
Classifier: License :: OSI Approved :: MIT License
Classifier: Operating System :: OS Independent
